{
  "app": "The Daily Drop",
  "date": "2025-11-02",
  "season": "Autumn",
  "hemisphere": "Northern",
  "title": "Cozy Autumn Nights",
  "oils": [
    "Cinnamon (Cinnamomum verum)",
    "Nutmeg (Myristica fragrans)",
    "Bergamot (Citrus aurantium bergamia)"
  ],
  "formats": {
    "diffuser": {
      "drops": {
        "Cinnamon": 10,
        "Nutmeg": 15,
        "Bergamot": 20
      },
      "notes": "Inhale for a calming evening atmosphere."
    },
    "roller": {
      "size_ml": 10,
      "dilution_percent": 2,
      "drops": {
        "Cinnamon": 10,
        "Nutmeg": 7,
        "Bergamot": 8
      },
      "carrier": "fractionated coconut oil"
    },
    "spray_optional": {
      "size_ml": 30,
      "drops": {
        "Cinnamon": 5,
        "Nutmeg": 7,
        "Bergamot": 10
      },
      "base": "distilled water + 95% ethanol",
      "note": "Shake well before use"
    }
  },
  "why_it_works": "Cinnamon and Nutmeg evoke warmth and coziness, while Bergamot adds a touch of citrus to uplift and balance.",
  "safety": [
    "Patch test; dilute for skin.",
    "Avoid eyes/mucosa; keep from children & pets.",
    "Do not ingest oils.",
    "Consult a professional if pregnant, nursing, or under care."
  ],
  "tags": [
    "Season:Autumn",
    "Mood:Relaxing",
    "Use:Evening"
  ]
}