{
  "app": "The Daily Drop",
  "date": "2026-05-14",
  "season": "Spring",
  "hemisphere": "Northern",
  "title": "Blooming Renewal",
  "oils": [
    "Lemon (Citrus limon)",
    "Geranium (Pelargonium graveolens)",
    "Bergamot (Citrus aurantium bergamia)"
  ],
  "formats": {
    "diffuser": {
      "drops": {
        "Lemon": 7,
        "Geranium": 3,
        "Bergamot": 5
      },
      "notes": "Uplift with a refreshing morning blend."
    },
    "roller": {
      "size_ml": 10,
      "dilution_percent": 2,
      "drops": {
        "Lemon": 7,
        "Geranium": 3,
        "Bergamot": 5
      },
      "carrier": "fractionated coconut oil"
    },
    "spray_optional": {
      "size_ml": 30,
      "drops": {
        "Lemon": 15,
        "Geranium": 7,
        "Bergamot": 10
      },
      "base": "distilled water + 95% ethanol",
      "note": "Shake well before use."
    }
  },
  "why_it_works": "Lemon uplifts and clarifies, while Geranium balances. Bergamot adds a soothing, floral touch.",
  "safety": [
    "Patch test; dilute for skin.",
    "Avoid eyes/mucosa; keep from children & pets.",
    "Do not ingest oils.",
    "Consult a professional if pregnant, nursing, or under care."
  ],
  "tags": [
    "Season:Spring",
    "Mood:Energized",
    "Use:Mood booster"
  ]
}