{
  "app": "The Daily Drop",
  "date": "2026-04-02",
  "season": "Spring",
  "hemisphere": "Northern",
  "title": "Blooming Renewal",
  "oils": [
    "Lemon (Citrus limon)",
    "Geranium (Pelargonium graveolens)",
    "Bergamot (Citrus aurantium bergamia)"
  ],
  "formats": {
    "diffuser": {
      "drops": {
        "Lemon": 10,
        "Geranium": 15,
        "Bergamot": 5
      },
      "notes": "Invigorating for a morning pick-me-up."
    },
    "roller": {
      "size_ml": 10,
      "dilution_percent": 2,
      "drops": {
        "Lemon": 5,
        "Geranium": 7,
        "Bergamot": 2
      },
      "carrier": "fractionated coconut oil"
    },
    "spray_optional": {
      "size_ml": 30,
      "drops": {
        "Lemon": 15,
        "Geranium": 20,
        "Bergamot": 5
      },
      "base": "distilled water + 95% ethanol",
      "note": "Shake well before each use."
    }
  },
  "why_it_works": "Lemon uplifts, while Geranium balances and Bergamot calms the senses.",
  "safety": [
    "Patch test; dilute for skin.",
    "Avoid eyes/mucosa; keep from children & pets.",
    "Do not ingest oils.",
    "Consult a professional if pregnant, nursing, or under care."
  ],
  "tags": [
    "Season:Spring",
    "Mood:Uplifting",
    "Use:Morning Routine"
  ]
}